ChudengSuanfaSuanfaXinjie06180339887498949/README.md
ChudengSuanfaSuanfaXinjie06180339887498949/__init__.py
ChudengSuanfaSuanfaXinjie06180339887498949/__main__.py
ChudengSuanfaSuanfaXinjie06180339887498949/file.pdf
ChudengSuanfaSuanfaXinjie06180339887498949/index.html
chudeng_suanfa_suanfa_xinjie_0_6180339887498949-2024.3.2.0.dist-info/METADATA
chudeng_suanfa_suanfa_xinjie_0_6180339887498949-2024.3.2.0.dist-info/WHEEL
chudeng_suanfa_suanfa_xinjie_0_6180339887498949-2024.3.2.0.dist-info/entry_points.txt
chudeng_suanfa_suanfa_xinjie_0_6180339887498949-2024.3.2.0.dist-info/top_level.txt
chudeng_suanfa_suanfa_xinjie_0_6180339887498949-2024.3.2.0.dist-info/RECORD
